youtube_playlist_to_m3u/__init__.py
youtube_playlist_to_m3u/main.py
youtube_playlist_to_m3u/tools.py
youtube_playlist_to_m3u-1.0.2.dist-info/AUTHORS.rst
youtube_playlist_to_m3u-1.0.2.dist-info/LICENSE.txt
youtube_playlist_to_m3u-1.0.2.dist-info/METADATA
youtube_playlist_to_m3u-1.0.2.dist-info/WHEEL
youtube_playlist_to_m3u-1.0.2.dist-info/entry_points.txt
youtube_playlist_to_m3u-1.0.2.dist-info/top_level.txt
youtube_playlist_to_m3u-1.0.2.dist-info/RECORD
