Metadata-Version: 2.1
Name: youtube-playlist-to-m3u
Version: 1.0.2
Summary: A quick tool to extract a M3U playlist from a youtube playlist url
Home-page: https://github.com/Arwalk/youtube_playlist_to_m3u
Author: Arwalk
License: mit
Project-URL: Documentation, https://pyscaffold.org/
Platform: any
Classifier: Development Status :: 4 - Beta
Classifier: Programming Language :: Python
Requires-Python: >=3.6
Requires-Dist: youtube-dl
Provides-Extra: testing
Requires-Dist: pytest ; extra == 'testing'
Requires-Dist: pytest-cov ; extra == 'testing'
